{
  "file": "Turbine_Data_Kelmarsh_3_2019-01-01_-_2020-01-01_230_cleaned.csv",
  "target_column": "Power (kW)",
  "feature_corr_threshold": 0.85,
  "target_corr_threshold": 0.1,
  "input_feature_count_before_pruning": 138,
  "feature_count_after_multicollinearity_pruning": 47,
  "excluded_columns_count": 84,
  "multicollinearity_dropped_columns_count": 91,
  "selected_features_count": 31,
  "selected_features": [
    "Wind speed (m/s)",
    "Transformer temperature (\u00b0C)",
    "Gear oil inlet temperature (\u00b0C)",
    "Front bearing temperature (\u00b0C)",
    "Current L2 / V, max (A)",
    "Power factor (cosphi)",
    "Reactive power, Standard deviation (kvar)",
    "Tower Acceleration y (mm/ss)",
    "Wind speed, Standard deviation (m/s)",
    "Nacelle temperature (\u00b0C)",
    "Generator bearing front temperature (\u00b0C)",
    "Motor current axis 1 (A)",
    "Stator temperature 1 (\u00b0C)",
    "Temp. top box (\u00b0C)",
    "Gear oil temperature (\u00b0C)",
    "Blade angle (pitch position) A, Min (\u00b0)",
    "Generator bearing rear temperature (\u00b0C)",
    "Gear oil temperature, Max (\u00b0C)",
    "Generator RPM, Standard deviation (RPM)",
    "Generator bearing rear temperature, Std (\u00b0C)",
    "Blade angle (pitch position) A (\u00b0)",
    "Blade angle (pitch position) A, Max (\u00b0)",
    "Long Term Wind (m/s)",
    "Gear oil temperature, Standard deviation (\u00b0C)",
    "Hub temperature, min (\u00b0C)",
    "Tower Acceleration X (mm/ss)",
    "Grid voltage, Standard deviation (V)",
    "Nacelle ambient temperature (\u00b0C)",
    "Voltage L1 / U (V)",
    "Voltage L1 / U, Min (V)",
    "Voltage L1 / U, Standard deviation (V)"
  ]
}